pylibsrcml/__init__.py
pylibsrcml/exception.py
pylibsrcml/gen_options.py
pylibsrcml/globals.py
pylibsrcml/options.py
pylibsrcml/srcml.py
pylibsrcml/srcml_archive.py
pylibsrcml/srcml_unit.py
pylibsrcml-1.0.0.post1.dist-info/LICENSE
pylibsrcml-1.0.0.post1.dist-info/METADATA
pylibsrcml-1.0.0.post1.dist-info/WHEEL
pylibsrcml-1.0.0.post1.dist-info/top_level.txt
pylibsrcml-1.0.0.post1.dist-info/RECORD
